{"color":"DEFAULT","isTrashed":false,"isPinned":false,"isArchived":false,"annotations":[{"description":"Contact forms are useful on websites if you want your users to be able to interact with you over email. And there are lots of ways to build them. Traditionally you'd have either used PHP for sending emails over the server or some third party service that would take care","source":"WEBLINK","title":"How to Build a Contact Form with SendGrid and Next.js","url":"https://www.freecodecamp.org/news/how-to-build-a-working-contact-form-with-sendgrid-and-next-js/"}],"textContent":"Contact form","title":"https://www.freecodecamp.org/news/how-to-build-a-working-contact-form-with-sendgrid-and-next-js/amp/","userEditedTimestampUsec":1670859557463000,"createdTimestampUsec":1670859557463000,"textContentHtml":"<p dir=\"ltr\" style=\"line-height:1.38;margin-top:0.0pt;margin-bottom:0.0pt;\"><span style=\"font-size:16.0pt;font-family:'Google Sans';color:#000000;background-color:transparent;font-weight:400;font-style:normal;font-variant:normal;text-decoration:none;vertical-align:baseline;white-space:pre;white-space:pre-wrap;\">Contact form<\/span><\/p>"}