{"color":"DEFAULT","isTrashed":false,"isPinned":false,"isArchived":false,"textContent":"LinkedList can easlily move elements, \n\nWhile array modification ( except adding to the end ) is O(1)  ","title":"LinkedList vs ArrayList ","userEditedTimestampUsec":1684345691600000,"createdTimestampUsec":1684345599744000,"textContentHtml":"<p dir=\"ltr\" style=\"line-height:1.38;margin-top:0.0pt;margin-bottom:0.0pt;\"><span style=\"font-size:16.0pt;font-family:'Google Sans';color:#000000;background-color:transparent;font-weight:400;font-style:normal;font-variant:normal;text-decoration:none;vertical-align:baseline;white-space:pre;white-space:pre-wrap;\">LinkedList can easlily move elements,&nbsp;<\/span><\/p><br /><p dir=\"ltr\" style=\"line-height:1.38;margin-top:0.0pt;margin-bottom:0.0pt;\"><span style=\"font-size:16.0pt;font-family:'Google Sans';color:#000000;background-color:transparent;font-weight:400;font-style:normal;font-variant:normal;text-decoration:none;vertical-align:baseline;white-space:pre;white-space:pre-wrap;\">While array modification ( except adding to the end ) is O(1)&nbsp; <\/span><\/p>","labels":[{"name":"Java"},{"name":"Algorithme"}]}